qrm/__init__.py
qrm/cli.py
qrm/qrm.ui
qrm/qrm_common.py
qrm/ui.py
qrm-0.2.0.dist-info/METADATA
qrm-0.2.0.dist-info/WHEEL
qrm-0.2.0.dist-info/entry_points.txt
qrm-0.2.0.dist-info/RECORD
