Metadata-Version: 2.1
Name: qrm
Version: 0.2.0
Summary: PyQt5 based reMarkable explorer
Home-page: https://projects.om-office.de/frans/qrm.git
Author: Frans Fürst
Author-email: frans.fuerst+gitlab@protonmail.com
Requires-Python: >=3.10,<4.0
Classifier: Programming Language :: Python :: 3
Classifier: Programming Language :: Python :: 3.10
Classifier: Programming Language :: Python :: 3.11
Requires-Dist: lxml (>=4.7,<5.0)
Requires-Dist: paramiko (>=2.8.0,<3.0.0)
Requires-Dist: pyqt5 (>=5.15,<6.0)
Requires-Dist: treelib (>=1.6.1,<2.0.0)
Project-URL: Repository, https://projects.om-office.de/frans/qrm.git
